MalFox/__init__.py
MalFox/__main__.py
MalFox-0.2.0.dist-info/LICENSE
MalFox-0.2.0.dist-info/METADATA
MalFox-0.2.0.dist-info/WHEEL
MalFox-0.2.0.dist-info/top_level.txt
MalFox-0.2.0.dist-info/RECORD
