Metadata-Version: 2.1
Name: MalFox
Version: 0.2.0
Summary: A locally-run cover generator for MyAnimeList.
Home-page: https://github.com/ValerioLyndon/MalFox
Author: Valerio Lyndon
License: MIT
Keywords: MyAnimeList,CSS,User Customization
Platform: UNKNOWN
Classifier: Programming Language :: Python :: 3.7
Classifier: License :: OSI Approved :: MIT License
Classifier: Operating System :: OS Independent
Requires-Dist: requests
